feast_cassandra_online_store/__init__.py
feast_cassandra_online_store/cassandra_online_store.py
feast_cassandra-0.1.4.dist-info/LICENSE.txt
feast_cassandra-0.1.4.dist-info/METADATA
feast_cassandra-0.1.4.dist-info/WHEEL
feast_cassandra-0.1.4.dist-info/top_level.txt
feast_cassandra-0.1.4.dist-info/RECORD
