Metadata-Version: 2.1
Name: feast-cassandra
Version: 0.1.4
Summary: Cassandra/Astra DB support for Feast online store
Home-page: https://github.com/datastaxdevs/feast-cassandra-online-store
Author: Stefano Lottini
Author-email: stefano.lottini@datastax.com
License: LICENSE.txt
Keywords: feast,cassandra,mlops
Platform: UNKNOWN
Classifier: Development Status :: 4 - Beta
Classifier: Environment :: Console
Classifier: Intended Audience :: Developers
Classifier: License :: OSI Approved :: Apache Software License
Classifier: Programming Language :: Python :: 3
Classifier: Programming Language :: Python :: 3.7
Classifier: Programming Language :: Python :: 3.8
Classifier: Programming Language :: Python :: 3.9
Classifier: Programming Language :: Python :: 3.10
Classifier: Programming Language :: Python :: 3.11
Classifier: Programming Language :: Python :: 3 :: Only
Requires-Python: >=3.7.0
Requires-Dist: cassandra-driver (<4,>=3.24.0)
